README
setup.py
cineworld/__init__.py
cineworld/cineworld.py
cineworld/cineworld_api_key.py
cineworld.egg-info/PKG-INFO
cineworld.egg-info/SOURCES.txt
cineworld.egg-info/dependency_links.txt
cineworld.egg-info/top_level.txt
test/test.py