Metadata-Version: 1.0
Name: cineworld
Version: 0.1.0
Summary: Cineworld API Wrapper
Home-page: https://github.com/oracal/cineworld
Author: Thomas Whitton
Author-email: mail@thomaswhitton.com
License: LICENSE.txt
Platform: UNKNOWN
